trac_github-2.3.dist-info/DESCRIPTION.rst
trac_github-2.3.dist-info/METADATA
trac_github-2.3.dist-info/RECORD
trac_github-2.3.dist-info/WHEEL
trac_github-2.3.dist-info/entry_points.txt
trac_github-2.3.dist-info/metadata.json
trac_github-2.3.dist-info/top_level.txt
tracext/__init__.py
tracext/github.py
