Metadata-Version: 2.0
Name: trac-github
Version: 2.3
Summary: Trac - GitHub integration
Home-page: https://github.com/trac-hacks/trac-github
Author: Aymeric Augustin
Author-email: aymeric.augustin@m4x.org
License: BSD
Download-URL: https://pypi.python.org/pypi/trac-github
Platform: all
Provides-Extra: oauth
Requires-Dist: requests-oauthlib (>=0.5); extra == 'oauth'
